scivae/__init__.py
scivae/contrastive_vae.py
scivae/conv_vae.py
scivae/loss.py
scivae/main.py
scivae/optimiser.py
scivae/sampler.py
scivae/save.py
scivae/stats.py
scivae/sup_vae.py
scivae/util.py
scivae/vae.py
scivae/validate.py
scivae/vis.py
scivae-1.1.1.data/data/LICENSE
scivae-1.1.1.dist-info/LICENSE
scivae-1.1.1.dist-info/METADATA
scivae-1.1.1.dist-info/WHEEL
scivae-1.1.1.dist-info/entry_points.txt
scivae-1.1.1.dist-info/top_level.txt
scivae-1.1.1.dist-info/RECORD
