Metadata-Version: 2.1
Name: scivae
Version: 1.1.1
Home-page: https://github.com/ArianeMora/scivae
Author: Ariane Mora
Author-email: ariane.n.mora@gmail.com
License: GPL3
Project-URL: Bug Tracker, https://github.com/ArianeMora/scivae/issues
Project-URL: Documentation, https://github.com/ArianeMora/scivae
Project-URL: Source Code, https://github.com/ArianeMora/scivae
Keywords: util
Classifier: Intended Audience :: Science/Research
Classifier: License :: OSI Approved :: GNU General Public License v3 (GPLv3)
Classifier: Natural Language :: English
Classifier: Operating System :: OS Independent
Classifier: Programming Language :: Python :: 3.6
Classifier: Programming Language :: Python :: 3.7
Classifier: Programming Language :: Python :: 3.8
Classifier: Topic :: Scientific/Engineering :: Bio-Informatics
Requires-Python: >=3.8
License-File: LICENSE
Requires-Dist: pandas
Requires-Dist: numpy
Requires-Dist: Keras>=2.4.3
Requires-Dist: Keras-Applications>=1.0.8
Requires-Dist: matplotlib>=3.3.3
Requires-Dist: sciutil
Requires-Dist: pyswarm
Requires-Dist: scikit-learn
Requires-Dist: tensorflow>=2.9
Requires-Dist: tf-keras
Requires-Dist: tensorflow-probability
Requires-Dist: seaborn
Requires-Dist: sciviso>=1.0.3
Requires-Dist: statsmodels
Requires-Dist: jupyterlab
